paul/tools/calendar.py
paul_calendar_tool-0.1.6.dist-info/licenses/LICENSE
paul_calendar_tool-0.1.6.dist-info/METADATA
paul_calendar_tool-0.1.6.dist-info/WHEEL
paul_calendar_tool-0.1.6.dist-info/top_level.txt
paul_calendar_tool-0.1.6.dist-info/RECORD
