Metadata-Version: 2.4
Name: paul-calendar-tool
Version: 0.1.6
Summary: Demo calendar tool (for educational use only)
Author-email: paul <paul@kfsoft.info>
License-Expression: MIT
Classifier: Programming Language :: Python :: 3
Classifier: Operating System :: OS Independent
Requires-Python: >=3.10
License-File: LICENSE
Requires-Dist: colorama
Dynamic: license-file
